waon/__init__.py
waon/_waon.cpython-312-x86_64-linux-gnu.so
waon-0.10.dist-info/METADATA
waon-0.10.dist-info/WHEEL
waon-0.10.dist-info/top_level.txt
waon-0.10.dist-info/RECORD
