Metadata-Version: 2.4
Name: waon
Version: 0.10
Summary: Python bindings for WaoN - Wave-to-Notes transcriber
Home-page: https://github.com/blazeiburgess/WaoN
Author: WaoN Development Team
Author-email: WaoN Development Team <kichiki@users.sourceforge.net>
License: GPL-2.0-or-later
Project-URL: Homepage, https://github.com/blazeiburgess/WaoN
Project-URL: Repository, https://github.com/blazeiburgess/WaoN.git
Project-URL: Bug Tracker, https://github.com/blazeiburgess/WaoN/issues
Keywords: audio,midi,transcription,music,signal-processing
Classifier: Development Status :: 4 - Beta
Classifier: Intended Audience :: Developers
Classifier: Intended Audience :: Science/Research
Classifier: License :: OSI Approved :: GNU General Public License v2 or later (GPLv2+)
Classifier: Operating System :: POSIX :: Linux
Classifier: Operating System :: MacOS
Classifier: Operating System :: Microsoft :: Windows
Classifier: Programming Language :: C
Classifier: Programming Language :: C++
Classifier: Programming Language :: Python :: 3
Classifier: Programming Language :: Python :: 3.6
Classifier: Programming Language :: Python :: 3.7
Classifier: Programming Language :: Python :: 3.8
Classifier: Programming Language :: Python :: 3.9
Classifier: Programming Language :: Python :: 3.10
Classifier: Programming Language :: Python :: 3.11
Classifier: Programming Language :: Python :: 3.12
Classifier: Topic :: Multimedia :: Sound/Audio :: Analysis
Classifier: Topic :: Multimedia :: Sound/Audio :: Conversion
Requires-Python: >=3.6
Requires-Dist: numpy>=1.16.0
Provides-Extra: dev
Requires-Dist: pytest>=6.0; extra == "dev"
Requires-Dist: pytest-cov; extra == "dev"
Requires-Dist: soundfile; extra == "dev"
Dynamic: author
Dynamic: description
Dynamic: description-content-type
Dynamic: home-page
Dynamic: requires-python
